{"schema_version": "akshare.raw.quotes.v1", "generated_at": "2026-02-18T09:48:08", "rows": [{"symbol_code": "002131", "latest": 8.96, "pct_change": -1.32, "turnover_cny": 11302922821.68, "volume_lot": 12421343.0, "open": 9.0, "high": 9.34, "low": 8.75, "prev_close": 9.08, "source": "akshare.stock_bid_ask_em", "ingest_ts": "2026-02-18T09:47:25"}, {"symbol_code": "300058", "latest": 19.0, "pct_change": -5.75, "turnover_cny": 9724703583.2, "volume_lot": 4959372.0, "open": 19.9, "high": 20.36, "low": 19.0, "prev_close": 20.16, "source": "akshare.stock_bid_ask_em", "ingest_ts": "2026-02-18T09:47:30"}, {"symbol_code": "002342", "latest": 15.44, "pct_change": -9.97, "turnover_cny": 368915640.0, "volume_lot": 238935.0, "open": 15.44, "high": 15.44, "low": 15.44, "prev_close": 17.15, "source": "akshare.stock_bid_ask_em", "ingest_ts": "2026-02-18T09:47:35"}, {"symbol_code": "600519", "latest": 1485.3, "pct_change": -0.09, "turnover_cny": 6216379203.0, "volume_lot": 41679.0, "open": 1486.6, "high": 1507.8, "low": 1470.58, "prev_close": 1486.6, "source": "akshare.stock_bid_ask_em", "ingest_ts": "2026-02-18T09:47:40"}, {"symbol_code": "300059", "latest": 22.37, "pct_change": -1.28, "turnover_cny": 4641832483.13, "volume_lot": 2054685.0, "open": 22.7, "high": 22.82, "low": 22.36, "prev_close": 22.66, "source": "akshare.stock_bid_ask_em", "ingest_ts": "2026-02-18T09:47:44"}, {"symbol_code": "600089", "latest": 28.75, "pct_change": -0.59, "turnover_cny": 5744209075.0, "volume_lot": 1999256.0, "open": 28.63, "high": 29.16, "low": 28.21, "prev_close": 28.92, "source": "akshare.stock_bid_ask_em", "ingest_ts": "2026-02-18T09:47:49"}, {"symbol_code": "600986", "latest": 12.56, "pct_change": -5.99, "turnover_cny": 3244038850.0, "volume_lot": 2514358.0, "open": 13.11, "high": 13.41, "low": 12.54, "prev_close": 13.36, "source": "akshare.stock_bid_ask_em", "ingest_ts": "2026-02-18T09:47:54"}, {"symbol_code": "601899", "latest": 37.78, "pct_change": -4.96, "turnover_cny": 12921954036.0, "volume_lot": 3380334.0, "open": 38.26, "high": 39.04, "low": 37.69, "prev_close": 39.75, "source": "akshare.stock_bid_ask_em", "ingest_ts": "2026-02-18T09:47:58"}, {"symbol_code": "002050", "latest": 53.48, "pct_change": 1.54, "turnover_cny": 6977349027.16, "volume_lot": 1307070.0, "open": 52.15, "high": 53.9, "low": 51.91, "prev_close": 52.67, "source": "akshare.stock_bid_ask_em", "ingest_ts": "2026-02-18T09:48:03"}, {"symbol_code": "002195", "latest": 9.93, "pct_change": -2.46, "turnover_cny": 3790927874.49, "volume_lot": 3795548.0, "open": 9.95, "high": 10.13, "low": 9.86, "prev_close": 10.18, "source": "akshare.stock_bid_ask_em", "ingest_ts": "2026-02-18T09:48:08"}], "errors": []}